drf_expiring_token/__init__.py
drf_expiring_token/admin.py
drf_expiring_token/apps.py
drf_expiring_token/authentication.py
drf_expiring_token/models.py
drf_expiring_token/serializers.py
drf_expiring_token/settings.py
drf_expiring_token/urls.py
drf_expiring_token/views.py
drf_expiring_token/migrations/0001_initial.py
drf_expiring_token/migrations/__init__.py
drf_expiring_token-1.1.2.dist-info/LICENSE
drf_expiring_token-1.1.2.dist-info/METADATA
drf_expiring_token-1.1.2.dist-info/WHEEL
drf_expiring_token-1.1.2.dist-info/top_level.txt
drf_expiring_token-1.1.2.dist-info/RECORD
